[{"answer_id":100,"answer_text_front_ja":"","answer_text_front_ja_phonetic":"","answer_text_rear_ja":"\u306e\u30b9\u30dd\u30fc\u30c4\u3092\u5fdc\u63f4\u3059\u308b\u306e\u304c\u597d\u304d\u3060\u3088","answer_text_rear_ja_phonetic":"\u304a\u3046\u3048\u3093,\u3059","answer_text_front_en":"","answer_text_front_en_phonetic":"","answer_text_rear_en":"","answer_text_rear_en_phonetic":"","word_id":37,"select_text":"\u30b9\u30dd\u30fc\u30c4","select_text_phonetic":"","one_point":"","one_point_phonetic":"","answer_text_rear_ja_phonetic_info":["6,7","12,12"]},{"answer_id":101,"answer_text_front_ja":"","answer_text_front_ja_phonetic":"","answer_text_rear_ja":"\u3092\u5fdc\u63f4\u3057\u3066\u308b\u3088","answer_text_rear_ja_phonetic":"\u304a\u3046\u3048\u3093","answer_text_front_en":"","answer_text_front_en_phonetic":"","answer_text_rear_en":"","answer_text_rear_en_phonetic":"","word_id":38,"select_text":"\u5fdc\u63f4\u3057\u3066\u308b\u3082\u306e","select_text_phonetic":"\u304a\u3046\u3048\u3093","one_point":"","one_point_phonetic":"","answer_text_rear_ja_phonetic_info":["1,2"],"select_text_phonetic_info":["0,1"]},{"answer_id":102,"answer_text_front_ja":"\u5fdc\u63f4\u3059\u308b\u3088\u308a\u3082\u81ea\u5206\u3067\u3084\u308a\u305f\u3044\u3088","answer_text_front_ja_phonetic":"\u304a\u3046\u3048\u3093,\u3058\u3076\u3093","answer_text_rear_ja":"","answer_text_rear_ja_phonetic":"","answer_text_front_en":"","answer_text_front_en_phonetic":"","answer_text_rear_en":"","answer_text_rear_en_phonetic":"","word_id":63,"select_text":" ","select_text_phonetic":"","one_point":"","one_point_phonetic":"","answer_text_front_ja_phonetic_info":["0,1","7,8"]}]