[{"answer_id":85,"answer_text_front_ja":"","answer_text_front_ja_phonetic":"","answer_text_rear_ja":"\u306e\u8272\u304c\u597d\u304d\u3060\u3088","answer_text_rear_ja_phonetic":"","answer_text_front_en":"","answer_text_front_en_phonetic":"","answer_text_rear_en":"","answer_text_rear_en_phonetic":"","word_id":28,"select_text":"\u8272","select_text_phonetic":"","one_point":""},{"answer_id":86,"answer_text_front_ja":"","answer_text_front_ja_phonetic":"","answer_text_rear_ja":"\u306e\u7d44\u307f\u5408\u308f\u305b\u304c\u597d\u304d\u3060\u3088","answer_text_rear_ja_phonetic":"","answer_text_front_en":"","answer_text_front_en_phonetic":"","answer_text_rear_en":"","answer_text_rear_en_phonetic":"","word_id":29,"select_text":"\u8272\u306e\u7d44\u307f\u5408\u308f\u305b","select_text_phonetic":"","one_point":""},{"answer_id":87,"answer_text_front_ja":"\u3069\u3093\u306a\u8272\u3067\u3082\u597d\u304d\u3060\u3088","answer_text_front_ja_phonetic":"","answer_text_rear_ja":"","answer_text_rear_ja_phonetic":"","answer_text_front_en":"","answer_text_front_en_phonetic":"","answer_text_rear_en":"","answer_text_rear_en_phonetic":"","word_id":63,"select_text":" ","select_text_phonetic":"","one_point":""}]