[{"answer_id":133,"answer_text_front_ja":"","answer_text_front_ja_phonetic":"","answer_text_rear_ja":"\u306e\u9078\u624b\u304c\u6700\u5f37\u3060\u3088","answer_text_rear_ja_phonetic":"\u305b\u3093\u3057\u3085,\u3055\u3044\u304d\u3087\u3046","answer_text_front_en":"","answer_text_front_en_phonetic":"","answer_text_rear_en":"","answer_text_rear_en_phonetic":"","word_id":53,"select_text":"\u30b9\u30dd\u30fc\u30c4","select_text_phonetic":"","one_point":"","one_point_phonetic":"","answer_text_rear_ja_phonetic_info":["1,2","4,5"]},{"answer_id":134,"answer_text_front_ja":"","answer_text_front_ja_phonetic":"","answer_text_rear_ja":"\u306e\u9078\u624b\u306f\u5f31\u305d\u3046\u3060\u306a\u3042","answer_text_rear_ja_phonetic":"\u305b\u3093\u3057\u3085,\u3088\u308f","answer_text_front_en":"","answer_text_front_en_phonetic":"","answer_text_rear_en":"","answer_text_rear_en_phonetic":"","word_id":54,"select_text":"\u30b9\u30dd\u30fc\u30c4","select_text_phonetic":"","one_point":"","one_point_phonetic":"","answer_text_rear_ja_phonetic_info":["1,2","4,4"]},{"answer_id":135,"answer_text_front_ja":"\u3088\u304f\u5206\u304b\u3089\u306a\u3044\u3088","answer_text_front_ja_phonetic":"\u308f","answer_text_rear_ja":"","answer_text_rear_ja_phonetic":"","answer_text_front_en":"","answer_text_front_en_phonetic":"","answer_text_rear_en":"","answer_text_rear_en_phonetic":"","word_id":63,"select_text":" ","select_text_phonetic":"","one_point":"","one_point_phonetic":"","answer_text_front_ja_phonetic_info":["2,2"]}]